{"available_scenarios": [{"Town05": [{"available_event_configurations": [{"transform": {"pitch": "0", "x": 31.5, "y": 69, "yaw": -90, "z": 0}, "_start_distance": 12.775577244535512, "_actor_vel": 4.9614152479619, "_start_distance2": 18.56938046054115, "_actor_vel2": 3.2765869256053826, "_brake": 0.7648364030029295, "_trigger_distance": 13.82835624031375, "_traffic_distance": 9.719365690271868, "weather": {"sun_altitude_angle": -75.03571197882123, "precipitation": 68.99160987744159, "wind_intensity": 81.74368969539742, "sun_azimuth_angle": 11.05452675906756, "fog_distance": "0", "cloudiness": 85.93335401094268, "fog_density": 44.71091527410239, "wetness": 36.35035308740223, "precipitation_deposits": 42.42549223723239}}], "scenario_type": "Scenario59"}], "Town03": [{"available_event_configurations": [{"transform": {"pitch": "0", "x": -86, "y": -81.9, "yaw": 90, "z": 0}, "_start_distance": 12.775577244535512, "_actor_vel": 4.9614152479619, "_start_distance2": 18.56938046054115, "_actor_vel2": 3.2765869256053826, "_brake": 0.7648364030029295, "_trigger_distance": 13.82835624031375, "_traffic_distance": 9.719365690271868, "weather": {"sun_altitude_angle": -75.03571197882123, "precipitation": 68.99160987744159, "wind_intensity": 81.74368969539742, "sun_azimuth_angle": 11.05452675906756, "fog_distance": "0", "cloudiness": 85.93335401094268, "fog_density": 44.71091527410239, "wetness": 36.35035308740223, "precipitation_deposits": 42.42549223723239}}], "scenario_type": "Scenario59"}]}]}