{"available_scenarios": [{"Town05": [{"available_event_configurations": [{"transform": {"pitch": "0", "x": 31.5, "y": 69, "yaw": -90, "z": 0}, "_start_distance": 14.861597147463035, "_actor_vel": 4.298932097430074, "_start_distance2": 18.997638051923648, "_actor_vel2": 3.4112294346723315, "_brake": 0.8890343660179336, "_trigger_distance": 13.973897831727294, "_traffic_distance": 5.4759650634713, "weather": {"sun_altitude_angle": -48.4436256898986, "precipitation": 6.5366646612585955, "wind_intensity": 84.2982349732182, "sun_azimuth_angle": 321.81802555450975, "fog_distance": "0", "cloudiness": 42.750880384315494, "fog_density": 38.48544874836226, "wetness": 57.602431026059165, "precipitation_deposits": 0.08965092951742637}}], "scenario_type": "Scenario59"}], "Town03": [{"available_event_configurations": [{"transform": {"pitch": "0", "x": -86, "y": -81.9, "yaw": 90, "z": 0}, "_start_distance": 14.861597147463035, "_actor_vel": 4.298932097430074, "_start_distance2": 18.997638051923648, "_actor_vel2": 3.4112294346723315, "_brake": 0.8890343660179336, "_trigger_distance": 13.973897831727294, "_traffic_distance": 5.4759650634713, "weather": {"sun_altitude_angle": -48.4436256898986, "precipitation": 6.5366646612585955, "wind_intensity": 84.2982349732182, "sun_azimuth_angle": 321.81802555450975, "fog_distance": "0", "cloudiness": 42.750880384315494, "fog_density": 38.48544874836226, "wetness": 57.602431026059165, "precipitation_deposits": 0.08965092951742637}}], "scenario_type": "Scenario59"}]}]}