{"available_scenarios": [{"Town05": [{"available_event_configurations": [{"transform": {"pitch": "0", "x": 31.5, "y": 69, "yaw": -90, "z": 0}, "_start_distance": 9.118706611474863, "_actor_vel": 4.393139123362422, "_start_distance2": 17.06064847351991, "_actor_vel2": 3.424362902318024, "_brake": 0.6853504225186724, "_trigger_distance": 12.150401688750076, "_traffic_distance": 9.729879145507194, "weather": {"sun_altitude_angle": 68.79642796968952, "precipitation": 18.325990021823422, "wind_intensity": 30.437346918562202, "sun_azimuth_angle": 291.7670479565995, "fog_distance": "0", "cloudiness": 70.57616090558962, "fog_density": 19.008797541071466, "wetness": 66.56138140246975, "precipitation_deposits": 61.92678501480394}}], "scenario_type": "Scenario59"}], "Town03": [{"available_event_configurations": [{"transform": {"pitch": "0", "x": -86, "y": -81.9, "yaw": 90, "z": 0}, "_start_distance": 9.118706611474863, "_actor_vel": 4.393139123362422, "_start_distance2": 17.06064847351991, "_actor_vel2": 3.424362902318024, "_brake": 0.6853504225186724, "_trigger_distance": 12.150401688750076, "_traffic_distance": 9.729879145507194, "weather": {"sun_altitude_angle": 68.79642796968952, "precipitation": 18.325990021823422, "wind_intensity": 30.437346918562202, "sun_azimuth_angle": 291.7670479565995, "fog_distance": "0", "cloudiness": 70.57616090558962, "fog_density": 19.008797541071466, "wetness": 66.56138140246975, "precipitation_deposits": 61.92678501480394}}], "scenario_type": "Scenario59"}]}]}