{"available_scenarios": [{"Town05": [{"available_event_configurations": [{"transform": {"pitch": "0", "x": 31.5, "y": 69, "yaw": -90, "z": 0}, "_start_distance": 12.032651620725346, "_actor_vel": 4.813912306152217, "_start_distance2": 17.026974021419747, "_actor_vel2": 3.424980826185392, "_brake": 0.8682632580130045, "_trigger_distance": 12.678480837948356, "_traffic_distance": 7.682241956931229, "weather": {"sun_altitude_angle": -1.299803076250953, "precipitation": 66.40238800578915, "wind_intensity": 78.7911426044685, "sun_azimuth_angle": 169.3631909383367, "fog_distance": "0", "cloudiness": 16.312217848573106, "fog_density": 39.084260195725626, "wetness": 45.39793666501729, "precipitation_deposits": 2.5055875743854594}}], "scenario_type": "Scenario59"}], "Town03": [{"available_event_configurations": [{"transform": {"pitch": "0", "x": -86, "y": -81.9, "yaw": 90, "z": 0}, "_start_distance": 12.032651620725346, "_actor_vel": 4.813912306152217, "_start_distance2": 17.026974021419747, "_actor_vel2": 3.424980826185392, "_brake": 0.8682632580130045, "_trigger_distance": 12.678480837948356, "_traffic_distance": 7.682241956931229, "weather": {"sun_altitude_angle": -1.299803076250953, "precipitation": 66.40238800578915, "wind_intensity": 78.7911426044685, "sun_azimuth_angle": 169.3631909383367, "fog_distance": "0", "cloudiness": 16.312217848573106, "fog_density": 39.084260195725626, "wetness": 45.39793666501729, "precipitation_deposits": 2.5055875743854594}}], "scenario_type": "Scenario59"}]}]}