{"available_scenarios": [{"Town05": [{"available_event_configurations": [{"transform": {"pitch": "0", "x": 31.5, "y": 69, "yaw": -90, "z": 0}, "_start_distance": 13.640709428047582, "_actor_vel": 4.221555608654108, "_start_distance2": 18.40897553665786, "_actor_vel2": 3.4413811507693466, "_brake": 0.5916851291208693, "_trigger_distance": 13.01861769222326, "_traffic_distance": 7.064390697993134, "weather": {"sun_altitude_angle": -24.963677053460003, "precipitation": 16.96613974953376, "wind_intensity": 61.00150102219507, "sun_azimuth_angle": 70.84829317570886, "fog_distance": "0", "cloudiness": 40.322149982424015, "fog_density": 69.53711025588186, "wetness": 29.585009819701625, "precipitation_deposits": 29.5636672345275}}], "scenario_type": "Scenario59"}], "Town03": [{"available_event_configurations": [{"transform": {"pitch": "0", "x": -86, "y": -81.9, "yaw": 90, "z": 0}, "_start_distance": 13.640709428047582, "_actor_vel": 4.221555608654108, "_start_distance2": 18.40897553665786, "_actor_vel2": 3.4413811507693466, "_brake": 0.5916851291208693, "_trigger_distance": 13.01861769222326, "_traffic_distance": 7.064390697993134, "weather": {"sun_altitude_angle": -24.963677053460003, "precipitation": 16.96613974953376, "wind_intensity": 61.00150102219507, "sun_azimuth_angle": 70.84829317570886, "fog_distance": "0", "cloudiness": 40.322149982424015, "fog_density": 69.53711025588186, "wetness": 29.585009819701625, "precipitation_deposits": 29.5636672345275}}], "scenario_type": "Scenario59"}]}]}