{"available_scenarios": [{"Town05": [{"available_event_configurations": [{"transform": {"pitch": "0", "x": 31.5, "y": 69, "yaw": -90, "z": 0}, "_start_distance": 13.616551730828338, "_actor_vel": 4.15029161445289, "_start_distance2": 15.923461006067164, "_actor_vel2": 3.3951884440917555, "_brake": 0.6702716154805679, "_trigger_distance": 14.076211750178109, "_traffic_distance": 6.8850792789299335, "weather": {"sun_altitude_angle": 63.37822421442863, "precipitation": 52.3901851397907, "wind_intensity": 17.063747064667023, "sun_azimuth_angle": 198.96497913982284, "fog_distance": "0", "cloudiness": 8.744617460466952, "fog_density": 4.265767327811365, "wetness": 15.396227397171646, "precipitation_deposits": 58.87005059089585}}], "scenario_type": "Scenario59"}], "Town03": [{"available_event_configurations": [{"transform": {"pitch": "0", "x": -86, "y": -81.9, "yaw": 90, "z": 0}, "_start_distance": 13.616551730828338, "_actor_vel": 4.15029161445289, "_start_distance2": 15.923461006067164, "_actor_vel2": 3.3951884440917555, "_brake": 0.6702716154805679, "_trigger_distance": 14.076211750178109, "_traffic_distance": 6.8850792789299335, "weather": {"sun_altitude_angle": 63.37822421442863, "precipitation": 52.3901851397907, "wind_intensity": 17.063747064667023, "sun_azimuth_angle": 198.96497913982284, "fog_distance": "0", "cloudiness": 8.744617460466952, "fog_density": 4.265767327811365, "wetness": 15.396227397171646, "precipitation_deposits": 58.87005059089585}}], "scenario_type": "Scenario59"}]}]}