{"available_scenarios": [{"Town05": [{"available_event_configurations": [{"transform": {"pitch": "0", "x": 31.5, "y": 69, "yaw": -90, "z": 0}, "_start_distance": 8.744210629079735, "_actor_vel": 4.70351790758687, "_start_distance2": 17.858359509849514, "_actor_vel2": 3.386748291609434, "_brake": 0.8201160820114886, "_trigger_distance": 14.09335857844734, "_traffic_distance": 9.48628562957477, "weather": {"sun_altitude_angle": -0.11808191781767619, "precipitation": 35.33974907932982, "wind_intensity": 28.147769141575772, "sun_azimuth_angle": 208.54467626387492, "fog_distance": "0", "cloudiness": 19.710520225208317, "fog_density": 92.7440843629347, "wetness": 52.96398878611449, "precipitation_deposits": 66.06122161103029}}], "scenario_type": "Scenario59"}], "Town03": [{"available_event_configurations": [{"transform": {"pitch": "0", "x": -86, "y": -81.9, "yaw": 90, "z": 0}, "_start_distance": 8.744210629079735, "_actor_vel": 4.70351790758687, "_start_distance2": 17.858359509849514, "_actor_vel2": 3.386748291609434, "_brake": 0.8201160820114886, "_trigger_distance": 14.09335857844734, "_traffic_distance": 9.48628562957477, "weather": {"sun_altitude_angle": -0.11808191781767619, "precipitation": 35.33974907932982, "wind_intensity": 28.147769141575772, "sun_azimuth_angle": 208.54467626387492, "fog_distance": "0", "cloudiness": 19.710520225208317, "fog_density": 92.7440843629347, "wetness": 52.96398878611449, "precipitation_deposits": 66.06122161103029}}], "scenario_type": "Scenario59"}]}]}