{"available_scenarios": [{"Town05": [{"available_event_configurations": [{"transform": {"pitch": "0", "x": 31.5, "y": 69, "yaw": -90, "z": 0}, "_start_distance": 8.335301839719708, "_actor_vel": 4.5033448071982916, "_start_distance2": 16.115253795316708, "_actor_vel2": 3.2851535968971257, "_brake": 0.6336547996857229, "_trigger_distance": 13.640912031081456, "_traffic_distance": 6.195412438026711, "weather": {"sun_altitude_angle": 68.68900254227617, "precipitation": 34.38687567664888, "wind_intensity": 35.75760493105706, "sun_azimuth_angle": 164.03884206630374, "fog_distance": "0", "cloudiness": 67.3520502648512, "fog_density": 86.18559675906286, "wetness": 37.15056954671571, "precipitation_deposits": 67.33309458367862}}], "scenario_type": "Scenario59"}], "Town03": [{"available_event_configurations": [{"transform": {"pitch": "0", "x": -86, "y": -81.9, "yaw": 90, "z": 0}, "_start_distance": 8.335301839719708, "_actor_vel": 4.5033448071982916, "_start_distance2": 16.115253795316708, "_actor_vel2": 3.2851535968971257, "_brake": 0.6336547996857229, "_trigger_distance": 13.640912031081456, "_traffic_distance": 6.195412438026711, "weather": {"sun_altitude_angle": 68.68900254227617, "precipitation": 34.38687567664888, "wind_intensity": 35.75760493105706, "sun_azimuth_angle": 164.03884206630374, "fog_distance": "0", "cloudiness": 67.3520502648512, "fog_density": 86.18559675906286, "wetness": 37.15056954671571, "precipitation_deposits": 67.33309458367862}}], "scenario_type": "Scenario59"}]}]}