{"available_scenarios": [{"Town05": [{"available_event_configurations": [{"transform": {"pitch": "0", "x": 31.5, "y": 69, "yaw": -90, "z": 0}, "_start_distance": 13.502152749733163, "_actor_vel": 4.948116892872437, "_start_distance2": 18.352271034448265, "_actor_vel2": 3.248701978948856, "_brake": 0.7194604566779944, "_trigger_distance": 13.728877048179282, "_traffic_distance": 5.320604600992683, "weather": {"sun_altitude_angle": -77.64187100924045, "precipitation": 4.495460275627671, "wind_intensity": 31.84790291283791, "sun_azimuth_angle": 341.868338881415, "fog_distance": "0", "cloudiness": 67.16933606256669, "fog_density": 68.49135514175049, "wetness": 2.859085643131898, "precipitation_deposits": 60.39010628315052}}], "scenario_type": "Scenario59"}], "Town03": [{"available_event_configurations": [{"transform": {"pitch": "0", "x": -86, "y": -81.9, "yaw": 90, "z": 0}, "_start_distance": 13.502152749733163, "_actor_vel": 4.948116892872437, "_start_distance2": 18.352271034448265, "_actor_vel2": 3.248701978948856, "_brake": 0.7194604566779944, "_trigger_distance": 13.728877048179282, "_traffic_distance": 5.320604600992683, "weather": {"sun_altitude_angle": -77.64187100924045, "precipitation": 4.495460275627671, "wind_intensity": 31.84790291283791, "sun_azimuth_angle": 341.868338881415, "fog_distance": "0", "cloudiness": 67.16933606256669, "fog_density": 68.49135514175049, "wetness": 2.859085643131898, "precipitation_deposits": 60.39010628315052}}], "scenario_type": "Scenario59"}]}]}