{"available_scenarios": [{"Town05": [{"available_event_configurations": [{"transform": {"pitch": "0", "x": 31.5, "y": 69, "yaw": -90, "z": 0}, "_start_distance": 10.314220736306654, "_actor_vel": 4.841453447652366, "_start_distance2": 15.9851104012797, "_actor_vel2": 3.050546685328527, "_brake": 0.8276862021087676, "_trigger_distance": 14.666845914589908, "_traffic_distance": 5.121257591927431, "weather": {"sun_altitude_angle": 28.238521702190013, "precipitation": 36.47649825478809, "wind_intensity": 55.43809621637102, "sun_azimuth_angle": 302.2938861428969, "fog_distance": "0", "cloudiness": 95.17973376428375, "fog_density": 3.9078311697433588, "wetness": 15.964192068943161, "precipitation_deposits": 17.830546369834334}}], "scenario_type": "Scenario59"}], "Town03": [{"available_event_configurations": [{"transform": {"pitch": "0", "x": -86, "y": -81.9, "yaw": 90, "z": 0}, "_start_distance": 10.314220736306654, "_actor_vel": 4.841453447652366, "_start_distance2": 15.9851104012797, "_actor_vel2": 3.050546685328527, "_brake": 0.8276862021087676, "_trigger_distance": 14.666845914589908, "_traffic_distance": 5.121257591927431, "weather": {"sun_altitude_angle": 28.238521702190013, "precipitation": 36.47649825478809, "wind_intensity": 55.43809621637102, "sun_azimuth_angle": 302.2938861428969, "fog_distance": "0", "cloudiness": 95.17973376428375, "fog_density": 3.9078311697433588, "wetness": 15.964192068943161, "precipitation_deposits": 17.830546369834334}}], "scenario_type": "Scenario59"}]}]}