{"available_scenarios": [{"Town05": [{"available_event_configurations": [{"transform": {"pitch": "0", "x": 35, "y": 130, "yaw": -90, "z": 0}, "_start_distance": 16.772835149762727, "_actor_vel": 2.0268041752301134, "_trigger_distance": 18.16163776448228, "_brake": 0.6725057617839418}, {"transform": {"pitch": "0", "x": 35, "y": 70, "yaw": -90, "z": 0}, "_start_distance": 16.772835149762727, "_actor_vel": 2.0268041752301134, "_trigger_distance": 18.16163776448228, "_brake": 0.6725057617839418, "weather": {"sun_altitude_angle": 5.841194723634393, "precipitation": 61.90580843598972, "wind_intensity": 85.61938916480618, "sun_azimuth_angle": 152.86071623669986, "fog_distance": "0", "cloudiness": 74.7886958132546, "fog_density": 0.6535546713789164, "wetness": 26.98233304567168, "precipitation_deposits": 50.1046713539686}}], "scenario_type": "Scenario39"}], "Town01": [{"available_event_configurations": [{"transform": {"pitch": "0", "x": 300, "y": 129, "yaw": 180, "z": 0}, "_start_distance": 16.772835149762727, "_actor_vel": 2.0268041752301134, "_trigger_distance": 18.16163776448228, "_brake": 0.6725057617839418, "weather": {"sun_altitude_angle": 5.841194723634393, "precipitation": 61.90580843598972, "wind_intensity": 85.61938916480618, "sun_azimuth_angle": 152.86071623669986, "fog_distance": "0", "cloudiness": 74.7886958132546, "fog_density": 0.6535546713789164, "wetness": 26.98233304567168, "precipitation_deposits": 50.1046713539686}}], "scenario_type": "Scenario39"}], "Town04": [{"available_event_configurations": [{"transform": {"pitch": "0", "x": 254.9, "y": -230.9, "yaw": 90, "z": 0}, "_start_distance": 16.772835149762727, "_actor_vel": 2.0268041752301134, "_trigger_distance": 18.16163776448228, "_brake": 0.6725057617839418, "weather": {"sun_altitude_angle": 5.841194723634393, "precipitation": 61.90580843598972, "wind_intensity": 85.61938916480618, "sun_azimuth_angle": 152.86071623669986, "fog_distance": "0", "cloudiness": 74.7886958132546, "fog_density": 0.6535546713789164, "wetness": 26.98233304567168, "precipitation_deposits": 50.1046713539686}}], "scenario_type": "Scenario39"}], "Town03": [{"available_event_configurations": [{"transform": {"pitch": "0", "x": -88.5, "y": -90, "yaw": 90, "z": 0}, "_start_distance": 16.772835149762727, "_actor_vel": 2.0268041752301134, "_trigger_distance": 18.16163776448228, "_brake": 0.6725057617839418, "weather": {"sun_altitude_angle": 5.841194723634393, "precipitation": 61.90580843598972, "wind_intensity": 85.61938916480618, "sun_azimuth_angle": 152.86071623669986, "fog_distance": "0", "cloudiness": 74.7886958132546, "fog_density": 0.6535546713789164, "wetness": 26.98233304567168, "precipitation_deposits": 50.1046713539686}}], "scenario_type": "Scenario39"}]}]}