{"available_scenarios": [{"Town05": [{"available_event_configurations": [{"transform": {"pitch": "0", "x": 35, "y": 130, "yaw": -90, "z": 0}, "_start_distance": 15.948666407879712, "_actor_vel": 2.252912167223061, "_trigger_distance": 17.92585460625483, "_brake": 0.9406968884651032}, {"transform": {"pitch": "0", "x": 35, "y": 70, "yaw": -90, "z": 0}, "_start_distance": 15.948666407879712, "_actor_vel": 2.252912167223061, "_trigger_distance": 17.92585460625483, "_brake": 0.9406968884651032, "weather": {"sun_altitude_angle": 2.5680026695016265, "precipitation": 92.9580889883256, "wind_intensity": 68.47720584251495, "sun_azimuth_angle": 352.9394183028907, "fog_distance": "0", "cloudiness": 22.443690457796663, "fog_density": 6.783685931395851, "wetness": 42.81711817527177, "precipitation_deposits": 78.82150523685604}}], "scenario_type": "Scenario39"}], "Town01": [{"available_event_configurations": [{"transform": {"pitch": "0", "x": 300, "y": 129, "yaw": 180, "z": 0}, "_start_distance": 15.948666407879712, "_actor_vel": 2.252912167223061, "_trigger_distance": 17.92585460625483, "_brake": 0.9406968884651032, "weather": {"sun_altitude_angle": 2.5680026695016265, "precipitation": 92.9580889883256, "wind_intensity": 68.47720584251495, "sun_azimuth_angle": 352.9394183028907, "fog_distance": "0", "cloudiness": 22.443690457796663, "fog_density": 6.783685931395851, "wetness": 42.81711817527177, "precipitation_deposits": 78.82150523685604}}], "scenario_type": "Scenario39"}], "Town04": [{"available_event_configurations": [{"transform": {"pitch": "0", "x": 254.9, "y": -230.9, "yaw": 90, "z": 0}, "_start_distance": 15.948666407879712, "_actor_vel": 2.252912167223061, "_trigger_distance": 17.92585460625483, "_brake": 0.9406968884651032, "weather": {"sun_altitude_angle": 2.5680026695016265, "precipitation": 92.9580889883256, "wind_intensity": 68.47720584251495, "sun_azimuth_angle": 352.9394183028907, "fog_distance": "0", "cloudiness": 22.443690457796663, "fog_density": 6.783685931395851, "wetness": 42.81711817527177, "precipitation_deposits": 78.82150523685604}}], "scenario_type": "Scenario39"}], "Town03": [{"available_event_configurations": [{"transform": {"pitch": "0", "x": -88.5, "y": -90, "yaw": 90, "z": 0}, "_start_distance": 15.948666407879712, "_actor_vel": 2.252912167223061, "_trigger_distance": 17.92585460625483, "_brake": 0.9406968884651032, "weather": {"sun_altitude_angle": 2.5680026695016265, "precipitation": 92.9580889883256, "wind_intensity": 68.47720584251495, "sun_azimuth_angle": 352.9394183028907, "fog_distance": "0", "cloudiness": 22.443690457796663, "fog_density": 6.783685931395851, "wetness": 42.81711817527177, "precipitation_deposits": 78.82150523685604}}], "scenario_type": "Scenario39"}]}]}