{"available_scenarios": [{"Town05": [{"available_event_configurations": [{"transform": {"pitch": "0", "x": 35, "y": 130, "yaw": -90, "z": 0}, "_start_distance": 16.589102706724105, "_actor_vel": 2.3256051036074807, "_trigger_distance": 17.532372716202495, "_brake": 0.5089767809270408}, {"transform": {"pitch": "0", "x": 35, "y": 70, "yaw": -90, "z": 0}, "_start_distance": 16.589102706724105, "_actor_vel": 2.3256051036074807, "_trigger_distance": 17.532372716202495, "_brake": 0.5089767809270408, "weather": {"sun_altitude_angle": 39.8866444836117, "precipitation": 22.18252967383335, "wind_intensity": 62.510039283484296, "sun_azimuth_angle": 202.08308188255327, "fog_distance": "0", "cloudiness": 70.87452073981243, "fog_density": 7.218499593302864, "wetness": 1.5267545666424631, "precipitation_deposits": 33.16963098652352}}], "scenario_type": "Scenario39"}], "Town01": [{"available_event_configurations": [{"transform": {"pitch": "0", "x": 300, "y": 129, "yaw": 180, "z": 0}, "_start_distance": 16.589102706724105, "_actor_vel": 2.3256051036074807, "_trigger_distance": 17.532372716202495, "_brake": 0.5089767809270408, "weather": {"sun_altitude_angle": 39.8866444836117, "precipitation": 22.18252967383335, "wind_intensity": 62.510039283484296, "sun_azimuth_angle": 202.08308188255327, "fog_distance": "0", "cloudiness": 70.87452073981243, "fog_density": 7.218499593302864, "wetness": 1.5267545666424631, "precipitation_deposits": 33.16963098652352}}], "scenario_type": "Scenario39"}], "Town04": [{"available_event_configurations": [{"transform": {"pitch": "0", "x": 254.9, "y": -230.9, "yaw": 90, "z": 0}, "_start_distance": 16.589102706724105, "_actor_vel": 2.3256051036074807, "_trigger_distance": 17.532372716202495, "_brake": 0.5089767809270408, "weather": {"sun_altitude_angle": 39.8866444836117, "precipitation": 22.18252967383335, "wind_intensity": 62.510039283484296, "sun_azimuth_angle": 202.08308188255327, "fog_distance": "0", "cloudiness": 70.87452073981243, "fog_density": 7.218499593302864, "wetness": 1.5267545666424631, "precipitation_deposits": 33.16963098652352}}], "scenario_type": "Scenario39"}], "Town03": [{"available_event_configurations": [{"transform": {"pitch": "0", "x": -88.5, "y": -90, "yaw": 90, "z": 0}, "_start_distance": 16.589102706724105, "_actor_vel": 2.3256051036074807, "_trigger_distance": 17.532372716202495, "_brake": 0.5089767809270408, "weather": {"sun_altitude_angle": 39.8866444836117, "precipitation": 22.18252967383335, "wind_intensity": 62.510039283484296, "sun_azimuth_angle": 202.08308188255327, "fog_distance": "0", "cloudiness": 70.87452073981243, "fog_density": 7.218499593302864, "wetness": 1.5267545666424631, "precipitation_deposits": 33.16963098652352}}], "scenario_type": "Scenario39"}]}]}