{"available_scenarios": [{"Town05": [{"available_event_configurations": [{"transform": {"pitch": "0", "x": 35, "y": 130, "yaw": -90, "z": 0}, "_start_distance": 17.798944969253654, "_actor_vel": 2.124160720043128, "_trigger_distance": 17.220784254148725, "_brake": 0.9906026664460471}, {"transform": {"pitch": "0", "x": 35, "y": 70, "yaw": -90, "z": 0}, "_start_distance": 17.798944969253654, "_actor_vel": 2.124160720043128, "_trigger_distance": 17.220784254148725, "_brake": 0.9906026664460471, "weather": {"sun_altitude_angle": 56.345985281342685, "precipitation": 75.02021323220829, "wind_intensity": 57.89569217070984, "sun_azimuth_angle": 257.16688414047746, "fog_distance": "0", "cloudiness": 96.89727766966567, "fog_density": 9.344057946991796, "wetness": 91.16413063773624, "precipitation_deposits": 5.593727171095642}}], "scenario_type": "Scenario39"}], "Town01": [{"available_event_configurations": [{"transform": {"pitch": "0", "x": 300, "y": 129, "yaw": 180, "z": 0}, "_start_distance": 17.798944969253654, "_actor_vel": 2.124160720043128, "_trigger_distance": 17.220784254148725, "_brake": 0.9906026664460471, "weather": {"sun_altitude_angle": 56.345985281342685, "precipitation": 75.02021323220829, "wind_intensity": 57.89569217070984, "sun_azimuth_angle": 257.16688414047746, "fog_distance": "0", "cloudiness": 96.89727766966567, "fog_density": 9.344057946991796, "wetness": 91.16413063773624, "precipitation_deposits": 5.593727171095642}}], "scenario_type": "Scenario39"}], "Town04": [{"available_event_configurations": [{"transform": {"pitch": "0", "x": 254.9, "y": -230.9, "yaw": 90, "z": 0}, "_start_distance": 17.798944969253654, "_actor_vel": 2.124160720043128, "_trigger_distance": 17.220784254148725, "_brake": 0.9906026664460471, "weather": {"sun_altitude_angle": 56.345985281342685, "precipitation": 75.02021323220829, "wind_intensity": 57.89569217070984, "sun_azimuth_angle": 257.16688414047746, "fog_distance": "0", "cloudiness": 96.89727766966567, "fog_density": 9.344057946991796, "wetness": 91.16413063773624, "precipitation_deposits": 5.593727171095642}}], "scenario_type": "Scenario39"}], "Town03": [{"available_event_configurations": [{"transform": {"pitch": "0", "x": -88.5, "y": -90, "yaw": 90, "z": 0}, "_start_distance": 17.798944969253654, "_actor_vel": 2.124160720043128, "_trigger_distance": 17.220784254148725, "_brake": 0.9906026664460471, "weather": {"sun_altitude_angle": 56.345985281342685, "precipitation": 75.02021323220829, "wind_intensity": 57.89569217070984, "sun_azimuth_angle": 257.16688414047746, "fog_distance": "0", "cloudiness": 96.89727766966567, "fog_density": 9.344057946991796, "wetness": 91.16413063773624, "precipitation_deposits": 5.593727171095642}}], "scenario_type": "Scenario39"}]}]}