{"available_scenarios": [{"Town05": [{"available_event_configurations": [{"transform": {"pitch": "0", "x": 35, "y": 70, "yaw": -90, "z": 0}, "_start_distance": 18.901435293391824, "_actor_vel": 3.110341922909071, "_trigger_distance": 6.888473603595541, "_brake": 1.0, "weather": {"sun_altitude_angle": -20.393040411366343, "precipitation": 69.69174773008602, "wind_intensity": 71.85333595310898, "sun_azimuth_angle": 359.26766536558387, "fog_distance": "0", "cloudiness": 33.032986576973535, "fog_density": 11.691041567118221, "wetness": 25.98355961108908, "precipitation_deposits": 88.0497726773263}}], "scenario_type": "Scenario57"}], "Town04": [{"available_event_configurations": [{"transform": {"pitch": "0", "x": -13.4, "y": -160, "yaw": 90, "z": 0}, "_start_distance": 18.901435293391824, "_actor_vel": 3.110341922909071, "_trigger_distance": 6.888473603595541, "_brake": 1.0, "weather": {"sun_altitude_angle": -20.393040411366343, "precipitation": 69.69174773008602, "wind_intensity": 71.85333595310898, "sun_azimuth_angle": 359.26766536558387, "fog_distance": "0", "cloudiness": 33.032986576973535, "fog_density": 11.691041567118221, "wetness": 25.98355961108908, "precipitation_deposits": 88.0497726773263}}], "scenario_type": "Scenario57"}], "Town03": [{"available_event_configurations": [{"transform": {"pitch": "0", "x": -88.5, "y": -90, "yaw": 90, "z": 0}, "_start_distance": 18.901435293391824, "_actor_vel": 3.110341922909071, "_trigger_distance": 6.888473603595541, "_brake": 1.0, "weather": {"sun_altitude_angle": -20.393040411366343, "precipitation": 69.69174773008602, "wind_intensity": 71.85333595310898, "sun_azimuth_angle": 359.26766536558387, "fog_distance": "0", "cloudiness": 33.032986576973535, "fog_density": 11.691041567118221, "wetness": 25.98355961108908, "precipitation_deposits": 88.0497726773263}}], "scenario_type": "Scenario57"}], "Town06": [{"available_event_configurations": [{"transform": {"pitch": "0", "x": 8.4, "y": 220, "yaw": -90, "z": 0}, "_start_distance": 18.901435293391824, "_actor_vel": 3.110341922909071, "_trigger_distance": 6.888473603595541, "_brake": 1.0, "weather": {"sun_altitude_angle": -20.393040411366343, "precipitation": 69.69174773008602, "wind_intensity": 71.85333595310898, "sun_azimuth_angle": 359.26766536558387, "fog_distance": "0", "cloudiness": 33.032986576973535, "fog_density": 11.691041567118221, "wetness": 25.98355961108908, "precipitation_deposits": 88.0497726773263}}], "scenario_type": "Scenario57"}]}]}