{"available_scenarios": [{"Town05": [{"available_event_configurations": [{"transform": {"pitch": "0", "x": 35, "y": 70, "yaw": -90, "z": 0}, "_start_distance": 17.6430729314171, "_actor_vel": 2.5326921422555717, "_trigger_distance": 8.823270281055034, "_brake": 1.0, "weather": {"sun_altitude_angle": 42.03537497642955, "precipitation": 66.20078100111499, "wind_intensity": 66.14339194584741, "sun_azimuth_angle": 359.1073926906749, "fog_distance": "0", "cloudiness": 63.98978259081897, "fog_density": 21.607803332482, "wetness": 34.451779256244706, "precipitation_deposits": 69.38309348889254}}], "scenario_type": "Scenario57"}], "Town04": [{"available_event_configurations": [{"transform": {"pitch": "0", "x": -13.4, "y": -160, "yaw": 90, "z": 0}, "_start_distance": 17.6430729314171, "_actor_vel": 2.5326921422555717, "_trigger_distance": 8.823270281055034, "_brake": 1.0, "weather": {"sun_altitude_angle": 42.03537497642955, "precipitation": 66.20078100111499, "wind_intensity": 66.14339194584741, "sun_azimuth_angle": 359.1073926906749, "fog_distance": "0", "cloudiness": 63.98978259081897, "fog_density": 21.607803332482, "wetness": 34.451779256244706, "precipitation_deposits": 69.38309348889254}}], "scenario_type": "Scenario57"}], "Town03": [{"available_event_configurations": [{"transform": {"pitch": "0", "x": -88.5, "y": -90, "yaw": 90, "z": 0}, "_start_distance": 17.6430729314171, "_actor_vel": 2.5326921422555717, "_trigger_distance": 8.823270281055034, "_brake": 1.0, "weather": {"sun_altitude_angle": 42.03537497642955, "precipitation": 66.20078100111499, "wind_intensity": 66.14339194584741, "sun_azimuth_angle": 359.1073926906749, "fog_distance": "0", "cloudiness": 63.98978259081897, "fog_density": 21.607803332482, "wetness": 34.451779256244706, "precipitation_deposits": 69.38309348889254}}], "scenario_type": "Scenario57"}], "Town06": [{"available_event_configurations": [{"transform": {"pitch": "0", "x": 8.4, "y": 220, "yaw": -90, "z": 0}, "_start_distance": 17.6430729314171, "_actor_vel": 2.5326921422555717, "_trigger_distance": 8.823270281055034, "_brake": 1.0, "weather": {"sun_altitude_angle": 42.03537497642955, "precipitation": 66.20078100111499, "wind_intensity": 66.14339194584741, "sun_azimuth_angle": 359.1073926906749, "fog_distance": "0", "cloudiness": 63.98978259081897, "fog_density": 21.607803332482, "wetness": 34.451779256244706, "precipitation_deposits": 69.38309348889254}}], "scenario_type": "Scenario57"}]}]}