{"available_scenarios": [{"Town05": [{"available_event_configurations": [{"transform": {"pitch": "0", "x": 35, "y": 130, "yaw": -90, "z": 0}, "_start_distance": 16.028782758047903, "_actor_vel": 2.407814975854637, "_trigger_distance": 17.8710597260099, "_model": 1}, {"transform": {"pitch": "0", "x": 35, "y": 65, "yaw": -90, "z": 0}, "_start_distance": 16.028782758047903, "_actor_vel": 2.407814975854637, "_trigger_distance": 17.8710597260099, "_model": 1, "weather": {"sun_altitude_angle": -56.08667512786899, "precipitation": 36.54088670444424, "wind_intensity": 32.27628651014105, "sun_azimuth_angle": 169.1813886950201, "fog_distance": "0", "cloudiness": 91.4203562021544, "fog_density": 65.21015359155847, "wetness": 58.78813883972847, "precipitation_deposits": 56.647243959870664}}], "scenario_type": "Scenario27"}], "Town01": [{"available_event_configurations": [{"transform": {"pitch": "0", "x": 312, "y": 129, "yaw": 180, "z": 0}, "_start_distance": 16.028782758047903, "_actor_vel": 2.407814975854637, "_trigger_distance": 17.8710597260099, "_model": 1, "weather": {"sun_altitude_angle": -56.08667512786899, "precipitation": 36.54088670444424, "wind_intensity": 32.27628651014105, "sun_azimuth_angle": 169.1813886950201, "fog_distance": "0", "cloudiness": 91.4203562021544, "fog_density": 65.21015359155847, "wetness": 58.78813883972847, "precipitation_deposits": 56.647243959870664}}], "scenario_type": "Scenario27"}], "Town04": [{"available_event_configurations": [{"transform": {"pitch": "0", "x": 254.9, "y": -230.9, "yaw": 90, "z": 0}, "_start_distance": 16.028782758047903, "_actor_vel": 2.407814975854637, "_trigger_distance": 17.8710597260099, "_model": 1, "weather": {"sun_altitude_angle": -56.08667512786899, "precipitation": 36.54088670444424, "wind_intensity": 32.27628651014105, "sun_azimuth_angle": 169.1813886950201, "fog_distance": "0", "cloudiness": 91.4203562021544, "fog_density": 65.21015359155847, "wetness": 58.78813883972847, "precipitation_deposits": 56.647243959870664}}], "scenario_type": "Scenario27"}], "Town03": [{"available_event_configurations": [{"transform": {"pitch": "0", "x": -88.5, "y": -90, "yaw": 90, "z": 0}, "_start_distance": 16.028782758047903, "_actor_vel": 2.407814975854637, "_trigger_distance": 17.8710597260099, "_model": 1, "weather": {"sun_altitude_angle": -56.08667512786899, "precipitation": 36.54088670444424, "wind_intensity": 32.27628651014105, "sun_azimuth_angle": 169.1813886950201, "fog_distance": "0", "cloudiness": 91.4203562021544, "fog_density": 65.21015359155847, "wetness": 58.78813883972847, "precipitation_deposits": 56.647243959870664}}], "scenario_type": "Scenario27"}]}]}