{"available_scenarios": [{"Town05": [{"available_event_configurations": [{"transform": {"pitch": "0", "x": 35, "y": 130, "yaw": -90, "z": 0}, "_start_distance": 19.221262924979463, "_actor_vel": 2.328633487871258, "_trigger_distance": 16.39995186205647, "_model": 1}, {"transform": {"pitch": "0", "x": 35, "y": 65, "yaw": -90, "z": 0}, "_start_distance": 19.221262924979463, "_actor_vel": 2.328633487871258, "_trigger_distance": 16.39995186205647, "_model": 1, "weather": {"sun_altitude_angle": 51.1786776509839, "precipitation": 60.86538312251937, "wind_intensity": 44.40442348619181, "sun_azimuth_angle": 230.53768037799992, "fog_distance": "0", "cloudiness": 61.46697338515591, "fog_density": 58.670536071792746, "wetness": 46.22742946498658, "precipitation_deposits": 91.61635754619162}}], "scenario_type": "Scenario27"}], "Town01": [{"available_event_configurations": [{"transform": {"pitch": "0", "x": 312, "y": 129, "yaw": 180, "z": 0}, "_start_distance": 19.221262924979463, "_actor_vel": 2.328633487871258, "_trigger_distance": 16.39995186205647, "_model": 1, "weather": {"sun_altitude_angle": 51.1786776509839, "precipitation": 60.86538312251937, "wind_intensity": 44.40442348619181, "sun_azimuth_angle": 230.53768037799992, "fog_distance": "0", "cloudiness": 61.46697338515591, "fog_density": 58.670536071792746, "wetness": 46.22742946498658, "precipitation_deposits": 91.61635754619162}}], "scenario_type": "Scenario27"}], "Town04": [{"available_event_configurations": [{"transform": {"pitch": "0", "x": 254.9, "y": -230.9, "yaw": 90, "z": 0}, "_start_distance": 19.221262924979463, "_actor_vel": 2.328633487871258, "_trigger_distance": 16.39995186205647, "_model": 1, "weather": {"sun_altitude_angle": 51.1786776509839, "precipitation": 60.86538312251937, "wind_intensity": 44.40442348619181, "sun_azimuth_angle": 230.53768037799992, "fog_distance": "0", "cloudiness": 61.46697338515591, "fog_density": 58.670536071792746, "wetness": 46.22742946498658, "precipitation_deposits": 91.61635754619162}}], "scenario_type": "Scenario27"}], "Town03": [{"available_event_configurations": [{"transform": {"pitch": "0", "x": -88.5, "y": -90, "yaw": 90, "z": 0}, "_start_distance": 19.221262924979463, "_actor_vel": 2.328633487871258, "_trigger_distance": 16.39995186205647, "_model": 1, "weather": {"sun_altitude_angle": 51.1786776509839, "precipitation": 60.86538312251937, "wind_intensity": 44.40442348619181, "sun_azimuth_angle": 230.53768037799992, "fog_distance": "0", "cloudiness": 61.46697338515591, "fog_density": 58.670536071792746, "wetness": 46.22742946498658, "precipitation_deposits": 91.61635754619162}}], "scenario_type": "Scenario27"}]}]}