{"available_scenarios": [{"Town05": [{"available_event_configurations": [{"transform": {"pitch": "0", "x": 35, "y": 130, "yaw": -90, "z": 0}, "_start_distance": 18.221018325840788, "_actor_vel": 2.0976038958254515, "_trigger_distance": 16.67884466544865, "_model": 1}, {"transform": {"pitch": "0", "x": 35, "y": 65, "yaw": -90, "z": 0}, "_start_distance": 18.221018325840788, "_actor_vel": 2.0976038958254515, "_trigger_distance": 16.67884466544865, "_model": 1, "weather": {"sun_altitude_angle": 31.210668109225693, "precipitation": 60.17770285754969, "wind_intensity": 62.408719214760886, "sun_azimuth_angle": 218.0567947783541, "fog_distance": "0", "cloudiness": 38.214110588013014, "fog_density": 98.69881453511854, "wetness": 86.85726700352076, "precipitation_deposits": 81.3686350026277}}], "scenario_type": "Scenario27"}], "Town01": [{"available_event_configurations": [{"transform": {"pitch": "0", "x": 312, "y": 129, "yaw": 180, "z": 0}, "_start_distance": 18.221018325840788, "_actor_vel": 2.0976038958254515, "_trigger_distance": 16.67884466544865, "_model": 1, "weather": {"sun_altitude_angle": 31.210668109225693, "precipitation": 60.17770285754969, "wind_intensity": 62.408719214760886, "sun_azimuth_angle": 218.0567947783541, "fog_distance": "0", "cloudiness": 38.214110588013014, "fog_density": 98.69881453511854, "wetness": 86.85726700352076, "precipitation_deposits": 81.3686350026277}}], "scenario_type": "Scenario27"}], "Town04": [{"available_event_configurations": [{"transform": {"pitch": "0", "x": 254.9, "y": -230.9, "yaw": 90, "z": 0}, "_start_distance": 18.221018325840788, "_actor_vel": 2.0976038958254515, "_trigger_distance": 16.67884466544865, "_model": 1, "weather": {"sun_altitude_angle": 31.210668109225693, "precipitation": 60.17770285754969, "wind_intensity": 62.408719214760886, "sun_azimuth_angle": 218.0567947783541, "fog_distance": "0", "cloudiness": 38.214110588013014, "fog_density": 98.69881453511854, "wetness": 86.85726700352076, "precipitation_deposits": 81.3686350026277}}], "scenario_type": "Scenario27"}], "Town03": [{"available_event_configurations": [{"transform": {"pitch": "0", "x": -88.5, "y": -90, "yaw": 90, "z": 0}, "_start_distance": 18.221018325840788, "_actor_vel": 2.0976038958254515, "_trigger_distance": 16.67884466544865, "_model": 1, "weather": {"sun_altitude_angle": 31.210668109225693, "precipitation": 60.17770285754969, "wind_intensity": 62.408719214760886, "sun_azimuth_angle": 218.0567947783541, "fog_distance": "0", "cloudiness": 38.214110588013014, "fog_density": 98.69881453511854, "wetness": 86.85726700352076, "precipitation_deposits": 81.3686350026277}}], "scenario_type": "Scenario27"}]}]}