{"available_scenarios": [{"Town05": [{"available_event_configurations": [{"transform": {"pitch": "0", "x": 35, "y": 130, "yaw": -90, "z": 0}, "_start_distance": 16.854165509444528, "_actor_vel": 2.1042668101790074, "_trigger_distance": 18.50272428781701, "_model": 1}, {"transform": {"pitch": "0", "x": 35, "y": 65, "yaw": -90, "z": 0}, "_start_distance": 16.854165509444528, "_actor_vel": 2.1042668101790074, "_trigger_distance": 18.50272428781701, "_model": 1, "weather": {"sun_altitude_angle": -72.61429758540251, "precipitation": 88.95446461556777, "wind_intensity": 79.51915862591699, "sun_azimuth_angle": 213.46389196760856, "fog_distance": "0", "cloudiness": 98.19235812813506, "fog_density": 69.175559188042, "wetness": 71.7436801343111, "precipitation_deposits": 82.87191975955275}}], "scenario_type": "Scenario27"}], "Town01": [{"available_event_configurations": [{"transform": {"pitch": "0", "x": 312, "y": 129, "yaw": 180, "z": 0}, "_start_distance": 16.854165509444528, "_actor_vel": 2.1042668101790074, "_trigger_distance": 18.50272428781701, "_model": 1, "weather": {"sun_altitude_angle": -72.61429758540251, "precipitation": 88.95446461556777, "wind_intensity": 79.51915862591699, "sun_azimuth_angle": 213.46389196760856, "fog_distance": "0", "cloudiness": 98.19235812813506, "fog_density": 69.175559188042, "wetness": 71.7436801343111, "precipitation_deposits": 82.87191975955275}}], "scenario_type": "Scenario27"}], "Town04": [{"available_event_configurations": [{"transform": {"pitch": "0", "x": 254.9, "y": -230.9, "yaw": 90, "z": 0}, "_start_distance": 16.854165509444528, "_actor_vel": 2.1042668101790074, "_trigger_distance": 18.50272428781701, "_model": 1, "weather": {"sun_altitude_angle": -72.61429758540251, "precipitation": 88.95446461556777, "wind_intensity": 79.51915862591699, "sun_azimuth_angle": 213.46389196760856, "fog_distance": "0", "cloudiness": 98.19235812813506, "fog_density": 69.175559188042, "wetness": 71.7436801343111, "precipitation_deposits": 82.87191975955275}}], "scenario_type": "Scenario27"}], "Town03": [{"available_event_configurations": [{"transform": {"pitch": "0", "x": -88.5, "y": -90, "yaw": 90, "z": 0}, "_start_distance": 16.854165509444528, "_actor_vel": 2.1042668101790074, "_trigger_distance": 18.50272428781701, "_model": 1, "weather": {"sun_altitude_angle": -72.61429758540251, "precipitation": 88.95446461556777, "wind_intensity": 79.51915862591699, "sun_azimuth_angle": 213.46389196760856, "fog_distance": "0", "cloudiness": 98.19235812813506, "fog_density": 69.175559188042, "wetness": 71.7436801343111, "precipitation_deposits": 82.87191975955275}}], "scenario_type": "Scenario27"}]}]}