{"available_scenarios": [{"Town05": [{"available_event_configurations": [{"transform": {"pitch": "0", "x": 35, "y": 130, "yaw": -90, "z": 0}, "_start_distance": 15.866343647335443, "_actor_vel": 2.002316253396863, "_trigger_distance": 15.892060262102296, "_model": 1}, {"transform": {"pitch": "0", "x": 35, "y": 65, "yaw": -90, "z": 0}, "_start_distance": 15.866343647335443, "_actor_vel": 2.002316253396863, "_trigger_distance": 15.892060262102296, "_model": 1, "weather": {"sun_altitude_angle": 12.198523737114186, "precipitation": 9.851434591089781, "wind_intensity": 72.95529838165487, "sun_azimuth_angle": 238.3104903528315, "fog_distance": "0", "cloudiness": 3.0603795175087822, "fog_density": 56.00913421724994, "wetness": 90.40547008784736, "precipitation_deposits": 29.063593309097392}}], "scenario_type": "Scenario27"}], "Town01": [{"available_event_configurations": [{"transform": {"pitch": "0", "x": 312, "y": 129, "yaw": 180, "z": 0}, "_start_distance": 15.866343647335443, "_actor_vel": 2.002316253396863, "_trigger_distance": 15.892060262102296, "_model": 1, "weather": {"sun_altitude_angle": 12.198523737114186, "precipitation": 9.851434591089781, "wind_intensity": 72.95529838165487, "sun_azimuth_angle": 238.3104903528315, "fog_distance": "0", "cloudiness": 3.0603795175087822, "fog_density": 56.00913421724994, "wetness": 90.40547008784736, "precipitation_deposits": 29.063593309097392}}], "scenario_type": "Scenario27"}], "Town04": [{"available_event_configurations": [{"transform": {"pitch": "0", "x": 254.9, "y": -230.9, "yaw": 90, "z": 0}, "_start_distance": 15.866343647335443, "_actor_vel": 2.002316253396863, "_trigger_distance": 15.892060262102296, "_model": 1, "weather": {"sun_altitude_angle": 12.198523737114186, "precipitation": 9.851434591089781, "wind_intensity": 72.95529838165487, "sun_azimuth_angle": 238.3104903528315, "fog_distance": "0", "cloudiness": 3.0603795175087822, "fog_density": 56.00913421724994, "wetness": 90.40547008784736, "precipitation_deposits": 29.063593309097392}}], "scenario_type": "Scenario27"}], "Town03": [{"available_event_configurations": [{"transform": {"pitch": "0", "x": -88.5, "y": -90, "yaw": 90, "z": 0}, "_start_distance": 15.866343647335443, "_actor_vel": 2.002316253396863, "_trigger_distance": 15.892060262102296, "_model": 1, "weather": {"sun_altitude_angle": 12.198523737114186, "precipitation": 9.851434591089781, "wind_intensity": 72.95529838165487, "sun_azimuth_angle": 238.3104903528315, "fog_distance": "0", "cloudiness": 3.0603795175087822, "fog_density": 56.00913421724994, "wetness": 90.40547008784736, "precipitation_deposits": 29.063593309097392}}], "scenario_type": "Scenario27"}]}]}