{"available_scenarios": [{"Town05": [{"available_event_configurations": [{"transform": {"pitch": "0", "x": 35, "y": 130, "yaw": -90, "z": 0}, "_start_distance": 18.553913570378203, "_actor_vel": 2.23265228499112, "_trigger_distance": 19.12830657876757, "_model": 1}, {"transform": {"pitch": "0", "x": 35, "y": 65, "yaw": -90, "z": 0}, "_start_distance": 18.553913570378203, "_actor_vel": 2.23265228499112, "_trigger_distance": 19.12830657876757, "_model": 1, "weather": {"sun_altitude_angle": 8.513576101110289, "precipitation": 69.10765169127632, "wind_intensity": 20.991421401083432, "sun_azimuth_angle": 86.00926526998285, "fog_distance": "0", "cloudiness": 53.22172214200568, "fog_density": 9.10518984063935, "wetness": 2.3402540713275077, "precipitation_deposits": 52.092478980501866}}], "scenario_type": "Scenario27"}], "Town01": [{"available_event_configurations": [{"transform": {"pitch": "0", "x": 312, "y": 129, "yaw": 180, "z": 0}, "_start_distance": 18.553913570378203, "_actor_vel": 2.23265228499112, "_trigger_distance": 19.12830657876757, "_model": 1, "weather": {"sun_altitude_angle": 8.513576101110289, "precipitation": 69.10765169127632, "wind_intensity": 20.991421401083432, "sun_azimuth_angle": 86.00926526998285, "fog_distance": "0", "cloudiness": 53.22172214200568, "fog_density": 9.10518984063935, "wetness": 2.3402540713275077, "precipitation_deposits": 52.092478980501866}}], "scenario_type": "Scenario27"}], "Town04": [{"available_event_configurations": [{"transform": {"pitch": "0", "x": 254.9, "y": -230.9, "yaw": 90, "z": 0}, "_start_distance": 18.553913570378203, "_actor_vel": 2.23265228499112, "_trigger_distance": 19.12830657876757, "_model": 1, "weather": {"sun_altitude_angle": 8.513576101110289, "precipitation": 69.10765169127632, "wind_intensity": 20.991421401083432, "sun_azimuth_angle": 86.00926526998285, "fog_distance": "0", "cloudiness": 53.22172214200568, "fog_density": 9.10518984063935, "wetness": 2.3402540713275077, "precipitation_deposits": 52.092478980501866}}], "scenario_type": "Scenario27"}], "Town03": [{"available_event_configurations": [{"transform": {"pitch": "0", "x": -88.5, "y": -90, "yaw": 90, "z": 0}, "_start_distance": 18.553913570378203, "_actor_vel": 2.23265228499112, "_trigger_distance": 19.12830657876757, "_model": 1, "weather": {"sun_altitude_angle": 8.513576101110289, "precipitation": 69.10765169127632, "wind_intensity": 20.991421401083432, "sun_azimuth_angle": 86.00926526998285, "fog_distance": "0", "cloudiness": 53.22172214200568, "fog_density": 9.10518984063935, "wetness": 2.3402540713275077, "precipitation_deposits": 52.092478980501866}}], "scenario_type": "Scenario27"}]}]}