{"available_scenarios": [{"Town05": [{"available_event_configurations": [{"transform": {"pitch": "0", "x": 35, "y": 130, "yaw": -90, "z": 0}, "_start_distance": 17.976761202336913, "_actor_vel": 2.446033840926843, "_trigger_distance": 17.44515884438792, "_model": 1}, {"transform": {"pitch": "0", "x": 35, "y": 65, "yaw": -90, "z": 0}, "_start_distance": 17.976761202336913, "_actor_vel": 2.446033840926843, "_trigger_distance": 17.44515884438792, "_model": 1, "weather": {"sun_altitude_angle": -12.008580250981936, "precipitation": 80.53479042210142, "wind_intensity": 40.50644735170002, "sun_azimuth_angle": 48.01035805164527, "fog_distance": "0", "cloudiness": 16.12511054564395, "fog_density": 39.97081407832268, "wetness": 88.32998589074742, "precipitation_deposits": 82.10030951375772}}], "scenario_type": "Scenario27"}], "Town01": [{"available_event_configurations": [{"transform": {"pitch": "0", "x": 312, "y": 129, "yaw": 180, "z": 0}, "_start_distance": 17.976761202336913, "_actor_vel": 2.446033840926843, "_trigger_distance": 17.44515884438792, "_model": 1, "weather": {"sun_altitude_angle": -12.008580250981936, "precipitation": 80.53479042210142, "wind_intensity": 40.50644735170002, "sun_azimuth_angle": 48.01035805164527, "fog_distance": "0", "cloudiness": 16.12511054564395, "fog_density": 39.97081407832268, "wetness": 88.32998589074742, "precipitation_deposits": 82.10030951375772}}], "scenario_type": "Scenario27"}], "Town04": [{"available_event_configurations": [{"transform": {"pitch": "0", "x": 254.9, "y": -230.9, "yaw": 90, "z": 0}, "_start_distance": 17.976761202336913, "_actor_vel": 2.446033840926843, "_trigger_distance": 17.44515884438792, "_model": 1, "weather": {"sun_altitude_angle": -12.008580250981936, "precipitation": 80.53479042210142, "wind_intensity": 40.50644735170002, "sun_azimuth_angle": 48.01035805164527, "fog_distance": "0", "cloudiness": 16.12511054564395, "fog_density": 39.97081407832268, "wetness": 88.32998589074742, "precipitation_deposits": 82.10030951375772}}], "scenario_type": "Scenario27"}], "Town03": [{"available_event_configurations": [{"transform": {"pitch": "0", "x": -88.5, "y": -90, "yaw": 90, "z": 0}, "_start_distance": 17.976761202336913, "_actor_vel": 2.446033840926843, "_trigger_distance": 17.44515884438792, "_model": 1, "weather": {"sun_altitude_angle": -12.008580250981936, "precipitation": 80.53479042210142, "wind_intensity": 40.50644735170002, "sun_azimuth_angle": 48.01035805164527, "fog_distance": "0", "cloudiness": 16.12511054564395, "fog_density": 39.97081407832268, "wetness": 88.32998589074742, "precipitation_deposits": 82.10030951375772}}], "scenario_type": "Scenario27"}]}]}