{"available_scenarios": [{"Town05": [{"available_event_configurations": [{"transform": {"pitch": "0", "x": 35, "y": 130, "yaw": -90, "z": 0}, "_start_distance": 15.369205714741701, "_actor_vel": 2.250650367236618, "_trigger_distance": 16.61143174703127, "_model": 1}, {"transform": {"pitch": "0", "x": 35, "y": 65, "yaw": -90, "z": 0}, "_start_distance": 15.369205714741701, "_actor_vel": 2.250650367236618, "_trigger_distance": 16.61143174703127, "_model": 1, "weather": {"sun_altitude_angle": 45.63099042687398, "precipitation": 29.326860911064724, "wind_intensity": 45.36806336754204, "sun_azimuth_angle": 304.6528982236156, "fog_distance": "0", "cloudiness": 5.661637862078717, "fog_density": 16.40790585405526, "wetness": 20.212565742639242, "precipitation_deposits": 96.26567522438249}}], "scenario_type": "Scenario27"}], "Town01": [{"available_event_configurations": [{"transform": {"pitch": "0", "x": 312, "y": 129, "yaw": 180, "z": 0}, "_start_distance": 15.369205714741701, "_actor_vel": 2.250650367236618, "_trigger_distance": 16.61143174703127, "_model": 1, "weather": {"sun_altitude_angle": 45.63099042687398, "precipitation": 29.326860911064724, "wind_intensity": 45.36806336754204, "sun_azimuth_angle": 304.6528982236156, "fog_distance": "0", "cloudiness": 5.661637862078717, "fog_density": 16.40790585405526, "wetness": 20.212565742639242, "precipitation_deposits": 96.26567522438249}}], "scenario_type": "Scenario27"}], "Town04": [{"available_event_configurations": [{"transform": {"pitch": "0", "x": 254.9, "y": -230.9, "yaw": 90, "z": 0}, "_start_distance": 15.369205714741701, "_actor_vel": 2.250650367236618, "_trigger_distance": 16.61143174703127, "_model": 1, "weather": {"sun_altitude_angle": 45.63099042687398, "precipitation": 29.326860911064724, "wind_intensity": 45.36806336754204, "sun_azimuth_angle": 304.6528982236156, "fog_distance": "0", "cloudiness": 5.661637862078717, "fog_density": 16.40790585405526, "wetness": 20.212565742639242, "precipitation_deposits": 96.26567522438249}}], "scenario_type": "Scenario27"}], "Town03": [{"available_event_configurations": [{"transform": {"pitch": "0", "x": -88.5, "y": -90, "yaw": 90, "z": 0}, "_start_distance": 15.369205714741701, "_actor_vel": 2.250650367236618, "_trigger_distance": 16.61143174703127, "_model": 1, "weather": {"sun_altitude_angle": 45.63099042687398, "precipitation": 29.326860911064724, "wind_intensity": 45.36806336754204, "sun_azimuth_angle": 304.6528982236156, "fog_distance": "0", "cloudiness": 5.661637862078717, "fog_density": 16.40790585405526, "wetness": 20.212565742639242, "precipitation_deposits": 96.26567522438249}}], "scenario_type": "Scenario27"}]}]}